pyptx_templar/__init__.py
pyptx_templar/copy.py
pyptx_templar/placeholder.py
pyptx_templar/presmanager.py
pyptx_templar/style.py
pyptx_templar/xml.py
pyptx_templar-0.1.10.dist-info/LICENSE
pyptx_templar-0.1.10.dist-info/METADATA
pyptx_templar-0.1.10.dist-info/WHEEL
pyptx_templar-0.1.10.dist-info/top_level.txt
pyptx_templar-0.1.10.dist-info/RECORD
