Metadata-Version: 2.1
Name: pyptx-templar
Version: 0.1.10
Summary: Easily fill PowerPoint templates with Python
License: MIT License        
Project-URL: Homepage, https://github.com/pgimalac/pyptx-templar
Keywords: template,PowerPoint,ppt,pptx,office
Classifier: License :: OSI Approved :: MIT License
Classifier: Environment :: Console
Classifier: Intended Audience :: Developers
Classifier: Operating System :: OS Independent
Classifier: Programming Language :: Python
Classifier: Programming Language :: Python :: 3
Classifier: Topic :: Office/Business :: Office Suites
Classifier: Topic :: Software Development :: Libraries
Requires-Python: >=3.6
License-File: LICENSE
Requires-Dist: python-pptx (==0.6.18)
Requires-Dist: Pillow
